{"version":{"fullVersion":"1.5.16","major":"1","minor":"5","patch":"16"},"meta":{"flags":["experimentalData"]},"collections":[{"label":"Pages","name":"page","path":"content/pages","format":"mdx","ui":{},"fields":[{"type":"object","list":true,"name":"blocks","label":"Sections","ui":{"visualSelector":true},"templates":[{"name":"hero","label":"Hero","ui":{"previewSrc":"/blocks/hero.png","defaultItem":{"tagline":"Here's some text above the other text","headline":"This Big Text is Totally Awesome","text":"Phasellus scelerisque, libero eu finibus rutrum, risus risus accumsan libero, nec molestie urna dui a leo."}},"fields":[{"type":"string","label":"Background","name":"background","options":[{"label":"Default","value":"bg-default"},{"label":"White","value":"bg-white/80"},{"label":"Gray","value":"bg-gray-50/80"},{"label":"Zinc","value":"bg-zinc-50"},{"label":"Black","value":"bg-black/80"},{"label":"Red","value":"bg-red-50/80"},{"label":"Orange","value":"bg-orange-50/80"},{"label":"Yellow","value":"bg-yellow-50/80"},{"label":"Green","value":"bg-green-50/80"},{"label":"Lime","value":"bg-lime-50/80"},{"label":"Emerald","value":"bg-emerald-50/80"},{"label":"Teal","value":"bg-teal-50/80"},{"label":"Cyan","value":"bg-cyan-50/80"},{"label":"Blue","value":"bg-blue-50/80"},{"label":"Sky","value":"bg-sky-50/80"},{"label":"Indigo","value":"bg-indigo-50/80"},{"label":"Violet","value":"bg-violet-50/80"},{"label":"Purple","value":"bg-purple-50/80"},{"label":"Fuchsia","value":"bg-fuchsia-50/80"},{"label":"Pink","value":"bg-pink-50/80"},{"label":"Rose","value":"bg-rose-50/80"}],"namespace":["page","blocks","hero","background"],"searchable":true,"uid":false},{"type":"string","label":"Headline","name":"headline","namespace":["page","blocks","hero","headline"],"searchable":true,"uid":false},{"type":"string","label":"Tagline","name":"tagline","namespace":["page","blocks","hero","tagline"],"searchable":true,"uid":false},{"label":"Actions","name":"actions","type":"object","list":true,"ui":{"defaultItem":{"label":"Action Label","type":"button","icon":true,"link":"/"}},"fields":[{"label":"Label","name":"label","type":"string","namespace":["page","blocks","hero","actions","label"]},{"label":"Type","name":"type","type":"string","options":[{"label":"Button","value":"button"},{"label":"Link","value":"link"}],"namespace":["page","blocks","hero","actions","type"]},{"type":"object","label":"Icon","name":"icon","fields":[{"type":"string","label":"Icon","name":"name","ui":{},"namespace":["page","blocks","hero","actions","icon","name"]},{"type":"string","label":"Color","name":"color","ui":{},"namespace":["page","blocks","hero","actions","icon","color"]},{"name":"style","label":"Style","type":"string","options":[{"label":"Circle","value":"circle"},{"label":"Float","value":"float"}],"namespace":["page","blocks","hero","actions","icon","style"]}],"namespace":["page","blocks","hero","actions","icon"]},{"label":"Link","name":"link","type":"string","namespace":["page","blocks","hero","actions","link"]}],"namespace":["page","blocks","hero","actions"],"searchable":true,"uid":false},{"type":"object","label":"Image","name":"image","fields":[{"name":"src","label":"Image Source","type":"image","namespace":["page","blocks","hero","image","src"]},{"name":"alt","label":"Alt Text","type":"string","namespace":["page","blocks","hero","image","alt"]},{"name":"videoUrl","label":"Video URL","type":"string","description":"If using a YouTube video, make sure to use the embed version of the video URL","namespace":["page","blocks","hero","image","videoUrl"]}],"namespace":["page","blocks","hero","image"],"searchable":true,"uid":false}],"namespace":["page","blocks","hero"]},{"name":"callout","label":"Callout","ui":{"previewSrc":"/blocks/callout.png","defaultItem":{"url":"https://tina.io/editorial-workflow","text":"Support for live editing and editorial workflow"}},"fields":[{"type":"string","label":"Background","name":"background","options":[{"label":"Default","value":"bg-default"},{"label":"White","value":"bg-white/80"},{"label":"Gray","value":"bg-gray-50/80"},{"label":"Zinc","value":"bg-zinc-50"},{"label":"Black","value":"bg-black/80"},{"label":"Red","value":"bg-red-50/80"},{"label":"Orange","value":"bg-orange-50/80"},{"label":"Yellow","value":"bg-yellow-50/80"},{"label":"Green","value":"bg-green-50/80"},{"label":"Lime","value":"bg-lime-50/80"},{"label":"Emerald","value":"bg-emerald-50/80"},{"label":"Teal","value":"bg-teal-50/80"},{"label":"Cyan","value":"bg-cyan-50/80"},{"label":"Blue","value":"bg-blue-50/80"},{"label":"Sky","value":"bg-sky-50/80"},{"label":"Indigo","value":"bg-indigo-50/80"},{"label":"Violet","value":"bg-violet-50/80"},{"label":"Purple","value":"bg-purple-50/80"},{"label":"Fuchsia","value":"bg-fuchsia-50/80"},{"label":"Pink","value":"bg-pink-50/80"},{"label":"Rose","value":"bg-rose-50/80"}],"namespace":["page","blocks","callout","background"],"searchable":true,"uid":false},{"type":"string","label":"Text","name":"text","namespace":["page","blocks","callout","text"],"searchable":true,"uid":false},{"type":"string","label":"Url","name":"url","namespace":["page","blocks","callout","url"],"searchable":true,"uid":false}],"namespace":["page","blocks","callout"]},{"name":"features","label":"Features","ui":{"previewSrc":"/blocks/features.png","defaultItem":{"title":"Built to cover your needs","description":"We have a lot of features to cover your needs","items":[{"title":"Here's Another Feature","text":"This is where you might talk about the feature, if this wasn't just filler text.","icon":{"color":"","style":"float","name":""}},{"title":"Here's Another Feature","text":"This is where you might talk about the feature, if this wasn't just filler text.","icon":{"color":"","style":"float","name":""}},{"title":"Here's Another Feature","text":"This is where you might talk about the feature, if this wasn't just filler text.","icon":{"color":"","style":"float","name":""}}]}},"fields":[{"type":"string","label":"Background","name":"background","options":[{"label":"Default","value":"bg-default"},{"label":"White","value":"bg-white/80"},{"label":"Gray","value":"bg-gray-50/80"},{"label":"Zinc","value":"bg-zinc-50"},{"label":"Black","value":"bg-black/80"},{"label":"Red","value":"bg-red-50/80"},{"label":"Orange","value":"bg-orange-50/80"},{"label":"Yellow","value":"bg-yellow-50/80"},{"label":"Green","value":"bg-green-50/80"},{"label":"Lime","value":"bg-lime-50/80"},{"label":"Emerald","value":"bg-emerald-50/80"},{"label":"Teal","value":"bg-teal-50/80"},{"label":"Cyan","value":"bg-cyan-50/80"},{"label":"Blue","value":"bg-blue-50/80"},{"label":"Sky","value":"bg-sky-50/80"},{"label":"Indigo","value":"bg-indigo-50/80"},{"label":"Violet","value":"bg-violet-50/80"},{"label":"Purple","value":"bg-purple-50/80"},{"label":"Fuchsia","value":"bg-fuchsia-50/80"},{"label":"Pink","value":"bg-pink-50/80"},{"label":"Rose","value":"bg-rose-50/80"}],"namespace":["page","blocks","features","background"],"searchable":true,"uid":false},{"type":"string","label":"Title","name":"title","namespace":["page","blocks","features","title"],"searchable":true,"uid":false},{"type":"string","label":"Description","name":"description","namespace":["page","blocks","features","description"],"searchable":true,"uid":false},{"type":"object","label":"Feature Items","name":"items","list":true,"ui":{"defaultItem":{"title":"Here's Another Feature","text":"This is where you might talk about the feature, if this wasn't just filler text.","icon":{"color":"","style":"float","name":""}}},"fields":[{"type":"object","label":"Icon","name":"icon","fields":[{"type":"string","label":"Icon","name":"name","ui":{},"namespace":["page","blocks","features","items","icon","name"]},{"type":"string","label":"Color","name":"color","ui":{},"namespace":["page","blocks","features","items","icon","color"]},{"name":"style","label":"Style","type":"string","options":[{"label":"Circle","value":"circle"},{"label":"Float","value":"float"}],"namespace":["page","blocks","features","items","icon","style"]}],"namespace":["page","blocks","features","items","icon"]},{"type":"string","label":"Title","name":"title","namespace":["page","blocks","features","items","title"]},{"type":"rich-text","label":"Text","name":"text","namespace":["page","blocks","features","items","text"]}],"namespace":["page","blocks","features","items"],"searchable":true,"uid":false}],"namespace":["page","blocks","features"]},{"name":"stats","label":"Stats","ui":{"previewSrc":"/blocks/stats.png","defaultItem":{"title":"TinaCMS by the numbers","description":"TinaCMS is an open-source content management system that allows developers to create and manage content for their websites and applications. It provides a flexible and customizable framework for building content-driven applications.","stats":[{"stat":"12K","type":"Stars on GitHub"},{"stat":"11K","type":"Active Users"},{"stat":"22K","type":"Powered Apps"}]}},"fields":[{"type":"string","label":"Background","name":"background","options":[{"label":"Default","value":"bg-default"},{"label":"White","value":"bg-white/80"},{"label":"Gray","value":"bg-gray-50/80"},{"label":"Zinc","value":"bg-zinc-50"},{"label":"Black","value":"bg-black/80"},{"label":"Red","value":"bg-red-50/80"},{"label":"Orange","value":"bg-orange-50/80"},{"label":"Yellow","value":"bg-yellow-50/80"},{"label":"Green","value":"bg-green-50/80"},{"label":"Lime","value":"bg-lime-50/80"},{"label":"Emerald","value":"bg-emerald-50/80"},{"label":"Teal","value":"bg-teal-50/80"},{"label":"Cyan","value":"bg-cyan-50/80"},{"label":"Blue","value":"bg-blue-50/80"},{"label":"Sky","value":"bg-sky-50/80"},{"label":"Indigo","value":"bg-indigo-50/80"},{"label":"Violet","value":"bg-violet-50/80"},{"label":"Purple","value":"bg-purple-50/80"},{"label":"Fuchsia","value":"bg-fuchsia-50/80"},{"label":"Pink","value":"bg-pink-50/80"},{"label":"Rose","value":"bg-rose-50/80"}],"namespace":["page","blocks","stats","background"],"searchable":true,"uid":false},{"type":"string","label":"Title","name":"title","namespace":["page","blocks","stats","title"],"searchable":true,"uid":false},{"type":"string","label":"Description","name":"description","namespace":["page","blocks","stats","description"],"searchable":true,"uid":false},{"type":"object","label":"Stats","name":"stats","list":true,"ui":{"defaultItem":{"stat":"12K","type":"Stars on GitHub"}},"fields":[{"type":"string","label":"Stat","name":"stat","namespace":["page","blocks","stats","stats","stat"]},{"type":"string","label":"Type","name":"type","namespace":["page","blocks","stats","stats","type"]}],"namespace":["page","blocks","stats","stats"],"searchable":true,"uid":false}],"namespace":["page","blocks","stats"]},{"name":"cta","label":"CTA","ui":{"previewSrc":"/blocks/cta.png","defaultItem":{"title":"Start Building","description":"Get started with TinaCMS today and take your content management to the next level.","actions":[{"label":"Get Started","type":"button","link":"/"},{"label":"Book Demo","type":"link","link":"/"}]}},"fields":[{"type":"string","label":"Title","name":"title","namespace":["page","blocks","cta","title"],"searchable":true,"uid":false},{"type":"string","label":"Description","name":"description","ui":{"component":"textarea"},"namespace":["page","blocks","cta","description"],"searchable":true,"uid":false},{"label":"Actions","name":"actions","type":"object","list":true,"ui":{"defaultItem":{"label":"Action Label","type":"button","icon":true,"link":"/"}},"fields":[{"label":"Label","name":"label","type":"string","namespace":["page","blocks","cta","actions","label"]},{"label":"Type","name":"type","type":"string","options":[{"label":"Button","value":"button"},{"label":"Link","value":"link"}],"namespace":["page","blocks","cta","actions","type"]},{"type":"object","label":"Icon","name":"icon","fields":[{"type":"string","label":"Icon","name":"name","ui":{},"namespace":["page","blocks","cta","actions","icon","name"]},{"type":"string","label":"Color","name":"color","ui":{},"namespace":["page","blocks","cta","actions","icon","color"]},{"name":"style","label":"Style","type":"string","options":[{"label":"Circle","value":"circle"},{"label":"Float","value":"float"}],"namespace":["page","blocks","cta","actions","icon","style"]}],"namespace":["page","blocks","cta","actions","icon"]},{"label":"Link","name":"link","type":"string","namespace":["page","blocks","cta","actions","link"]}],"namespace":["page","blocks","cta","actions"],"searchable":true,"uid":false}],"namespace":["page","blocks","cta"]},{"name":"content","label":"Content","ui":{"previewSrc":"/blocks/content.png","defaultItem":{"body":"Lorem ipsum dolor sit amet, consectetuer adipiscing elit. Donec odio. Quisque volutpat mattis eros. Nullam malesuada erat ut turpis. Suspendisse urna nibh, viverra non, semper suscipit, posuere a, pede."}},"fields":[{"type":"string","label":"Background","name":"background","options":[{"label":"Default","value":"bg-default"},{"label":"White","value":"bg-white/80"},{"label":"Gray","value":"bg-gray-50/80"},{"label":"Zinc","value":"bg-zinc-50"},{"label":"Black","value":"bg-black/80"},{"label":"Red","value":"bg-red-50/80"},{"label":"Orange","value":"bg-orange-50/80"},{"label":"Yellow","value":"bg-yellow-50/80"},{"label":"Green","value":"bg-green-50/80"},{"label":"Lime","value":"bg-lime-50/80"},{"label":"Emerald","value":"bg-emerald-50/80"},{"label":"Teal","value":"bg-teal-50/80"},{"label":"Cyan","value":"bg-cyan-50/80"},{"label":"Blue","value":"bg-blue-50/80"},{"label":"Sky","value":"bg-sky-50/80"},{"label":"Indigo","value":"bg-indigo-50/80"},{"label":"Violet","value":"bg-violet-50/80"},{"label":"Purple","value":"bg-purple-50/80"},{"label":"Fuchsia","value":"bg-fuchsia-50/80"},{"label":"Pink","value":"bg-pink-50/80"},{"label":"Rose","value":"bg-rose-50/80"}],"namespace":["page","blocks","content","background"],"searchable":true,"uid":false},{"type":"rich-text","label":"Body","name":"body","namespace":["page","blocks","content","body"],"searchable":true,"parser":{"type":"mdx"},"uid":false}],"namespace":["page","blocks","content"]},{"name":"testimonial","label":"Testimonial","ui":{"previewSrc":"/blocks/testimonial.png","defaultItem":{"testimonials":[{"quote":"There are only two hard things in Computer Science: cache invalidation and naming things.","author":"Phil Karlton"}]}},"fields":[{"type":"string","label":"Background","name":"background","options":[{"label":"Default","value":"bg-default"},{"label":"White","value":"bg-white/80"},{"label":"Gray","value":"bg-gray-50/80"},{"label":"Zinc","value":"bg-zinc-50"},{"label":"Black","value":"bg-black/80"},{"label":"Red","value":"bg-red-50/80"},{"label":"Orange","value":"bg-orange-50/80"},{"label":"Yellow","value":"bg-yellow-50/80"},{"label":"Green","value":"bg-green-50/80"},{"label":"Lime","value":"bg-lime-50/80"},{"label":"Emerald","value":"bg-emerald-50/80"},{"label":"Teal","value":"bg-teal-50/80"},{"label":"Cyan","value":"bg-cyan-50/80"},{"label":"Blue","value":"bg-blue-50/80"},{"label":"Sky","value":"bg-sky-50/80"},{"label":"Indigo","value":"bg-indigo-50/80"},{"label":"Violet","value":"bg-violet-50/80"},{"label":"Purple","value":"bg-purple-50/80"},{"label":"Fuchsia","value":"bg-fuchsia-50/80"},{"label":"Pink","value":"bg-pink-50/80"},{"label":"Rose","value":"bg-rose-50/80"}],"namespace":["page","blocks","testimonial","background"],"searchable":true,"uid":false},{"type":"string","label":"Title","name":"title","namespace":["page","blocks","testimonial","title"],"searchable":true,"uid":false},{"type":"string","label":"Description","name":"description","ui":{"component":"textarea"},"namespace":["page","blocks","testimonial","description"],"searchable":true,"uid":false},{"type":"object","list":true,"label":"Testimonials","name":"testimonials","ui":{"defaultItem":{"quote":"There are only two hard things in Computer Science: cache invalidation and naming things.","author":"Phil Karlton"}},"fields":[{"type":"string","ui":{"component":"textarea"},"label":"Quote","name":"quote","namespace":["page","blocks","testimonial","testimonials","quote"]},{"type":"string","label":"Author","name":"author","namespace":["page","blocks","testimonial","testimonials","author"]},{"type":"string","label":"Role","name":"role","namespace":["page","blocks","testimonial","testimonials","role"]},{"type":"image","label":"Avatar","name":"avatar","namespace":["page","blocks","testimonial","testimonials","avatar"]}],"namespace":["page","blocks","testimonial","testimonials"],"searchable":true,"uid":false}],"namespace":["page","blocks","testimonial"]},{"name":"video","label":"Video","ui":{"previewSrc":"/blocks/video.png","defaultItem":{"url":"https://www.youtube.com/watch?v=j8egYW7Jpgk"}},"fields":[{"type":"string","label":"Background","name":"background","options":[{"label":"Default","value":"bg-default"},{"label":"White","value":"bg-white/80"},{"label":"Gray","value":"bg-gray-50/80"},{"label":"Zinc","value":"bg-zinc-50"},{"label":"Black","value":"bg-black/80"},{"label":"Red","value":"bg-red-50/80"},{"label":"Orange","value":"bg-orange-50/80"},{"label":"Yellow","value":"bg-yellow-50/80"},{"label":"Green","value":"bg-green-50/80"},{"label":"Lime","value":"bg-lime-50/80"},{"label":"Emerald","value":"bg-emerald-50/80"},{"label":"Teal","value":"bg-teal-50/80"},{"label":"Cyan","value":"bg-cyan-50/80"},{"label":"Blue","value":"bg-blue-50/80"},{"label":"Sky","value":"bg-sky-50/80"},{"label":"Indigo","value":"bg-indigo-50/80"},{"label":"Violet","value":"bg-violet-50/80"},{"label":"Purple","value":"bg-purple-50/80"},{"label":"Fuchsia","value":"bg-fuchsia-50/80"},{"label":"Pink","value":"bg-pink-50/80"},{"label":"Rose","value":"bg-rose-50/80"}],"namespace":["page","blocks","video","background"],"searchable":true,"uid":false},{"type":"string","label":"Color","name":"color","options":[{"label":"Default","value":"default"},{"label":"Tint","value":"tint"},{"label":"Primary","value":"primary"}],"namespace":["page","blocks","video","color"],"searchable":true,"uid":false},{"type":"string","label":"Url","name":"url","namespace":["page","blocks","video","url"],"searchable":true,"uid":false},{"type":"boolean","label":"Auto Play","name":"autoPlay","namespace":["page","blocks","video","autoPlay"],"searchable":true,"uid":false},{"type":"boolean","label":"Loop","name":"loop","namespace":["page","blocks","video","loop"],"searchable":true,"uid":false}],"namespace":["page","blocks","video"]}],"namespace":["page","blocks"],"searchable":true,"uid":false}],"namespace":["page"]},{"label":"Blog Posts","name":"post","path":"content/posts","format":"mdx","ui":{},"fields":[{"type":"string","label":"Title","name":"title","isTitle":true,"required":true,"namespace":["post","title"],"searchable":true,"uid":false},{"type":"image","name":"heroImg","label":"Hero Image","namespace":["post","heroImg"],"searchable":false,"uid":false},{"type":"rich-text","label":"Excerpt","name":"excerpt","overrides":{"toolbar":["bold","italic","link"]},"namespace":["post","excerpt"],"searchable":true,"parser":{"type":"mdx"},"uid":false},{"type":"reference","label":"Author","name":"author","collections":["author"],"namespace":["post","author"],"searchable":true,"uid":false},{"type":"datetime","label":"Posted Date","name":"date","ui":{"dateFormat":"MMMM DD YYYY","timeFormat":"hh:mm A"},"namespace":["post","date"],"searchable":true,"uid":false},{"type":"rich-text","label":"Body","name":"_body","templates":[{"name":"BlockQuote","label":"Block Quote","fields":[{"name":"children","label":"Quote","type":"rich-text","overrides":{"toolbar":["bold","italic","link"]},"namespace":["post","_body","BlockQuote","children"],"searchable":true,"parser":{"type":"mdx"},"uid":false},{"name":"authorName","label":"Author","type":"string","namespace":["post","_body","BlockQuote","authorName"],"searchable":true,"uid":false}],"namespace":["post","_body","BlockQuote"]},{"name":"DateTime","label":"Date & Time","inline":true,"fields":[{"name":"format","label":"Format","type":"string","options":["utc","iso","local"],"namespace":["post","_body","DateTime","format"],"searchable":true,"uid":false}],"namespace":["post","_body","DateTime"]},{"name":"NewsletterSignup","label":"Newsletter Sign Up","fields":[{"name":"children","label":"CTA","type":"rich-text","namespace":["post","_body","NewsletterSignup","children"],"searchable":true,"parser":{"type":"mdx"},"uid":false},{"name":"placeholder","label":"Placeholder","type":"string","namespace":["post","_body","NewsletterSignup","placeholder"],"searchable":true,"uid":false},{"name":"buttonText","label":"Button Text","type":"string","namespace":["post","_body","NewsletterSignup","buttonText"],"searchable":true,"uid":false},{"name":"disclaimer","label":"Disclaimer","type":"rich-text","overrides":{"toolbar":["bold","italic","link"]},"namespace":["post","_body","NewsletterSignup","disclaimer"],"searchable":true,"parser":{"type":"mdx"},"uid":false}],"ui":{"defaultItem":{"placeholder":"Enter your email","buttonText":"Notify Me"}},"namespace":["post","_body","NewsletterSignup"]},{"name":"video","label":"Video","ui":{"previewSrc":"/blocks/video.png","defaultItem":{"url":"https://www.youtube.com/watch?v=j8egYW7Jpgk"}},"fields":[{"type":"string","label":"Background","name":"background","options":[{"label":"Default","value":"bg-default"},{"label":"White","value":"bg-white/80"},{"label":"Gray","value":"bg-gray-50/80"},{"label":"Zinc","value":"bg-zinc-50"},{"label":"Black","value":"bg-black/80"},{"label":"Red","value":"bg-red-50/80"},{"label":"Orange","value":"bg-orange-50/80"},{"label":"Yellow","value":"bg-yellow-50/80"},{"label":"Green","value":"bg-green-50/80"},{"label":"Lime","value":"bg-lime-50/80"},{"label":"Emerald","value":"bg-emerald-50/80"},{"label":"Teal","value":"bg-teal-50/80"},{"label":"Cyan","value":"bg-cyan-50/80"},{"label":"Blue","value":"bg-blue-50/80"},{"label":"Sky","value":"bg-sky-50/80"},{"label":"Indigo","value":"bg-indigo-50/80"},{"label":"Violet","value":"bg-violet-50/80"},{"label":"Purple","value":"bg-purple-50/80"},{"label":"Fuchsia","value":"bg-fuchsia-50/80"},{"label":"Pink","value":"bg-pink-50/80"},{"label":"Rose","value":"bg-rose-50/80"}],"namespace":["post","_body","video","background"],"searchable":true,"uid":false},{"type":"string","label":"Color","name":"color","options":[{"label":"Default","value":"default"},{"label":"Tint","value":"tint"},{"label":"Primary","value":"primary"}],"namespace":["post","_body","video","color"],"searchable":true,"uid":false},{"type":"string","label":"Url","name":"url","namespace":["post","_body","video","url"],"searchable":true,"uid":false},{"type":"boolean","label":"Auto Play","name":"autoPlay","namespace":["post","_body","video","autoPlay"],"searchable":true,"uid":false},{"type":"boolean","label":"Loop","name":"loop","namespace":["post","_body","video","loop"],"searchable":true,"uid":false}],"namespace":["post","_body","video"]}],"isBody":true,"namespace":["post","_body"],"searchable":true,"parser":{"type":"mdx"},"uid":false}],"namespace":["post"]},{"label":"Authors","name":"author","path":"content/authors","format":"md","fields":[{"type":"string","label":"Name","name":"name","isTitle":true,"required":true,"namespace":["author","name"],"searchable":true,"uid":false},{"type":"image","label":"Avatar","name":"avatar","namespace":["author","avatar"],"searchable":false,"uid":false}],"namespace":["author"]},{"label":"Global","name":"global","path":"content/global","format":"json","ui":{"global":true},"fields":[{"type":"object","label":"Header","name":"header","fields":[{"type":"object","label":"Icon","name":"icon","fields":[{"type":"string","label":"Icon","name":"name","ui":{},"namespace":["global","header","icon","name"],"searchable":true,"uid":false},{"type":"string","label":"Color","name":"color","ui":{},"namespace":["global","header","icon","color"],"searchable":true,"uid":false},{"name":"style","label":"Style","type":"string","options":[{"label":"Circle","value":"circle"},{"label":"Float","value":"float"}],"namespace":["global","header","icon","style"],"searchable":true,"uid":false}],"namespace":["global","header","icon"],"searchable":true,"uid":false},{"type":"string","label":"Name","name":"name","namespace":["global","header","name"],"searchable":true,"uid":false},{"type":"string","label":"Color","name":"color","options":[{"label":"Default","value":"default"},{"label":"Primary","value":"primary"}],"namespace":["global","header","color"],"searchable":true,"uid":false},{"type":"object","label":"Nav Links","name":"nav","list":true,"ui":{"defaultItem":{"href":"home","label":"Home"}},"fields":[{"type":"string","label":"Link","name":"href","namespace":["global","header","nav","href"],"searchable":true,"uid":false},{"type":"string","label":"Label","name":"label","namespace":["global","header","nav","label"],"searchable":true,"uid":false}],"namespace":["global","header","nav"],"searchable":true,"uid":false}],"namespace":["global","header"],"searchable":true,"uid":false},{"type":"object","label":"Footer","name":"footer","fields":[{"type":"object","label":"Social Links","name":"social","list":true,"ui":{},"fields":[{"type":"object","label":"Icon","name":"icon","fields":[{"type":"string","label":"Icon","name":"name","ui":{},"namespace":["global","footer","social","icon","name"],"searchable":true,"uid":false},{"type":"string","label":"Color","name":"color","ui":{},"namespace":["global","footer","social","icon","color"],"searchable":true,"uid":false},{"name":"style","label":"Style","type":"string","options":[{"label":"Circle","value":"circle"},{"label":"Float","value":"float"}],"namespace":["global","footer","social","icon","style"],"searchable":true,"uid":false}],"namespace":["global","footer","social","icon"],"searchable":true,"uid":false},{"type":"string","label":"Url","name":"url","namespace":["global","footer","social","url"],"searchable":true,"uid":false}],"namespace":["global","footer","social"],"searchable":true,"uid":false}],"namespace":["global","footer"],"searchable":true,"uid":false},{"type":"object","label":"Theme","name":"theme","fields":[{"type":"string","label":"Primary Color","name":"color","ui":{},"namespace":["global","theme","color"],"searchable":true,"uid":false},{"type":"string","name":"font","label":"Font Family","options":[{"label":"System Sans","value":"sans"},{"label":"Nunito","value":"nunito"},{"label":"Lato","value":"lato"}],"namespace":["global","theme","font"],"searchable":true,"uid":false},{"type":"string","name":"darkMode","label":"Dark Mode","options":[{"label":"System","value":"system"},{"label":"Light","value":"light"},{"label":"Dark","value":"dark"}],"namespace":["global","theme","darkMode"],"searchable":true,"uid":false}],"namespace":["global","theme"],"searchable":true,"uid":false}],"namespace":["global"]}],"config":{"media":{"tina":{"publicFolder":"public","mediaRoot":"uploads"}}}}